LoggingWebsocketHandler.py
LoggingWebsocketHandler-0.1.2.2.dist-info/DESCRIPTION.rst
LoggingWebsocketHandler-0.1.2.2.dist-info/METADATA
LoggingWebsocketHandler-0.1.2.2.dist-info/RECORD
LoggingWebsocketHandler-0.1.2.2.dist-info/WHEEL
LoggingWebsocketHandler-0.1.2.2.dist-info/metadata.json
LoggingWebsocketHandler-0.1.2.2.dist-info/top_level.txt
